setup.py
gotemp/__init__.py
gotemp/constants.py
gotemp/device.py
gotemp.egg-info/PKG-INFO
gotemp.egg-info/SOURCES.txt
gotemp.egg-info/dependency_links.txt
gotemp.egg-info/top_level.txt